technify/__init__.py
technify/indicators.py
technify/portfolio.py
technify/stock.py
technify/utils.py
technify-0.8.0.dist-info/DESCRIPTION.rst
technify-0.8.0.dist-info/METADATA
technify-0.8.0.dist-info/RECORD
technify-0.8.0.dist-info/WHEEL
technify-0.8.0.dist-info/metadata.json
technify-0.8.0.dist-info/top_level.txt
