Metadata-Version: 2.0
Name: technify
Version: 0.8.0
Summary: A framework to run technical analysis. Powered by pandas and ta-lib.
Home-page: https://github.com/rubenafo/technify
Author: Ruben Afonso
Author-email: rbfrancos@gmail.com
License: UNKNOWN
Download-URL: https://github.com/rubenafo/technify/archive/0.8.0.zip
Keywords: technical-analysis,pandas,finance,stock,ta-lib
Platform: UNKNOWN
Requires-Dist: quandl
Requires-Dist: ta-lib
